{
    "areas": [
        {
            "nome": "Montanha",
            "tipos": [
                "rock",
                "ground",
                "flying",
                "steel",
                "dragon",
                "normal-dragon",
                "dragon-fighting",
                "rock-ground",
                "ground-steel",
                "fire-ground",
                "rock-eletric",
                "steel-dragon",
                "rock-flying",
                "psychic-flying",
                "electric-flying",
                "electric-dragon",
                "fighting-flying",
                "dark-flying",
                "rock-fighting",
                "dragon-flying",
                "fire-flying",
                "steel-ground",
                "steel-psychic",
                "bug-rock",
                "steel-flying",
                "dark-fire",
                "rock-dark",
                "fire-fighting",
                "ground-dragon",
                "rock-psychic",
                "rock-steel",
                "dragon-ground",
                "ground-dark",
                "normal-ground"
            ]
        },
        {
            "nome": "Montanha nevada",
            "tipos": [
                "dragon-flying",
                "rock-steel",
                "ice-flying",
                "dragon-ice",
                "dragon"
            ]
        },
        {
            "nome": "Gelo",
            "tipos": [
                "ice-bug",
                "ice-ground",
                "ice-steel",
                "ice-fairy",
                "ice-psychic",
                "ice",
                "fighting-ice",
                "electric-ice",
                "ice-flying",
                "grass-ice",
                "ice-ghost",
                "electric-ice",
                "ice-fire"
            ]
        },
        {
            "nome": "Floresta",
            "tipos": [
                "bug-flying",
                "bug-poison",
                "bug-fire",
                "bug-ground",
                "poison",
                "fairy",
                "normal-fairy",
                "bug",
                "grass",
                "bug-steel",
                "flying-steel",
                "bug-fighting",
                "bug-grass",
                "poison-fighting"
            ]
        },
        {
            "nome": "Floresta sombria",
            "tipos": [
                "bug-flying",
                "bug-poison",
                "bug-fire",
                "grass-dark",
                "dark",
                "bug-ground",
                "bug-ghost",
                "dark-fighting",
                "dark-normal",
                "dark-flying",
                "grass-psychic",
                "poison",
                "poison-ground",
                "ghost-dark",
                "bug-psychic"
            ]
        },
        {
            "nome": "Campo",
            "tipos": [
                "poison",
                "fairy",
                "bug",
                "grass-fighting",
                "grass",
                "fighting",
                "flying",
                "grass-poison",
                "bug-grass",
                "normal",
                "grass-flying",
                "normal-flying",
                "grass-fighting",
                "grass-psychic",
                "poison-ground",
                "psychic-fairy",
                "fighting-psychic",
                "grass-dragon",
                "normal-psychic",
                "rock-grass",
                "rock-bug",
                "grass-ground",
                "fighting-steel",
                "psychic-fighting",
                "electric-grass",
                "grass-fairy",
                "bug-eletric",
                "grass-steel",
                "steel-fighting"
            ]
        },
        {
            "nome": "Caverna no gelo",
            "tipos": [
                "ice",
                "dark",
                "ice-dark",
                "ice-ground",
                "ground-flying",
                "rock-ice"
            ]
        },
        {
            "nome": "Caverna",
            "tipos": [
                "poison-flying",
                "poison",
                "poison-fairy",
                "fairy",
                "normal-fairy",
                "fairy-flying",
                "rock",
                "rock",
                "ground-flying",
                "dark-ice",
                "psychic-flying",
                "rock-fairy"
            ]
        },
        {
            "nome": "Montanha de fogo",
            "tipos": [
                "fire",
                "fire-flying",
                "fire-rock",
                "poison-fire",
                "electric-fire",
                "fire-psychic",
                "fire-normal",
                "fire-dark",
                "fire-dragon"
            ]
        },
        {
            "nome": "Agua",
            "tipos": [
                "water",
                "water-poison",
                "water-psychic",
                "water-flying",
                "water-electric",
                "water-steel"
            ]
        },
        {
            "nome": "Cidade",
            "tipos": [
                "psychic",
                "electric-steel",
                "electric",
                "steel",
                "normal",
                "ground-psychic",
                "fairy-steel",
                "electric-ghost",
                "flying-psychic",
                "electric-poison",
                "electric-fire",
                "electric-water",
                "electric-ice",
                "electric-grass",
                "ground-eletric",
                "ground-steel",
                "bug-eletric",
                "steel-eletric",
                "electric-dark",
                "electric-flying",
                "electric-normal",
                "electric-fairy",
                "steel-fairy"
            ]
        },
        {
            "nome": "Beira d'agua",
            "tipos": [
                "water-psychic",
                "water-fighting",
                "bug-water",
                "poison-psychic",
                "water-flying",
                "water-rock",
                "water-fairy",
                "water-ground",
                "water-dragon",
                "normal-water",
                "poison-dragon",
                "water-bug"
            ]
        },
        {
            "nome": "Aguas profundas",
            "tipos": [
                "water-dragon",
                "water-dark",
                "water-ghost",
                "dark-psychic"
            ]
        },
        {
            "nome": "Aguas geladas",
            "tipos": [
                "water-ice"
            ]
        },
        {
            "nome": "Caverna na montanha",
            "tipos": [
                "dark-dragon",
                "ground",
                "poison",
                "normal-dark",
                "ground",
                "dragon-ghost",
                "rock-dragon",
                "dragon",
                "flying-dragon"
            ]
        },
        {
            "nome": "Cemiterio",
            "tipos": [
                "dark-steel",
                "ghost-poison",
                "dark",
                "poison-dark",
                "ghost-fairy",
                "dark-fairy",
                "fire-ghost",
                "dark-flying",
                "ghost",
                "ground-ghost",
                "ghost-flying",
                "ghost-dark",
                "ice-ghost",
                "fire-ghost",
                "electric-ghost",
                "steel-ghost",
                "ghost-grass"
            ]
        }
    ]
}